framextract/__init__.py
framextract/__main__.py
frame_extractor-0.2.3.dist-info/LICENSE
frame_extractor-0.2.3.dist-info/METADATA
frame_extractor-0.2.3.dist-info/WHEEL
frame_extractor-0.2.3.dist-info/entry_points.txt
frame_extractor-0.2.3.dist-info/top_level.txt
frame_extractor-0.2.3.dist-info/RECORD
