Metadata-Version: 2.1
Name: frame-extractor
Version: 0.2.3
Summary: Extract frames from a video
Home-page: https://github.com/FirmaTechnologies/framextract
Author: ngchanway
Author-email: chan_way@firma-tech.com
License: GPL-3.0
Platform: UNKNOWN
Classifier: Development Status :: 4 - Beta
Classifier: License :: OSI Approved :: GNU General Public License v3 (GPLv3)
Classifier: Programming Language :: Python :: 3
Classifier: Topic :: Multimedia :: Video
Requires-Dist: numpy
Requires-Dist: opencv-python
